{"metadata": {"dataVersion": "2", "matchId": "NA1_4291710848", "participants": ["4n6VLbg0pk_cueIdBdSBhlzIeg7m7G8fj8VfcI8P9EZQyn3vph468NQBzzemIWDqo0YswFDjXUN08Q", "vPALV7WzY-yWXhPd5SGk-XTIurDbsmSfOWFuavqCFVysq5VMG-QZNEp5U3_gB4UUcoBoIOyt6ph_0g", "sZ9mXtRpVdxMfxeJBOXLC2csxtHaDlAz0anLy84BN0f839y19CoveIAWupE8kfOHWz6oTHYf9ajbjw", "CDPynCM5iJ18TN1yr8lYy8VaXsGt7oNlAnoXeGfUuG5Meu_Nai71zAOG8J6T31njfEI2EvQ-tOMF2g", "bTenuSCiBSHCzB02XDnJK8WBNKKwPgwigTGI6df1lA6_CbzIR0JYa0NYyN7qa1F6Gks0FqlfQXjR1Q", "hg-weySh2vJHoAZ-Lpo40D-YCAJtUcEwI_fJ0D-5nnx8-bvcyiOvENLZhVd1msfhUdWf7EDnpqYhjg", "ylH3YxKCmkgWy3X_u-bGPNy4cX9oF9KWMLHrTtA9vgTYC-6KSlnLXJ3YPNLkAMIGn2c79_YS7dyLxQ", "iCY13jSZ3RTBcwsKGFV5VogSuneSxeAgc46b0dJyOm2JfVq-6ia0PVOgPOXLFMO2tabELO7wz5hLeA", "uwBIYGc0A4XQuA2ILGlnlX0sRFg-zwQRaBIUumq2trvOV0YpS73ldfGlaGfwSLU61ojJ4y2ZDE7eUw", "gRdqveymmyp1r-3uSL9i6T8vgHQ0upQBuElh61qgUjqz_6HnKNeBRQ7pc7Do70DQJXDuJkJemdVrHA"]}, "info": {"gameCreation": 1651199794000, "gameDuration": 1286, "gameEndTimestamp": 1651201106596, "gameId": 4291710848, "gameMode": "CLASSIC", "gameName": "teambuilder-match-4291710848", "gameStartTimestamp": 1651199820573, "gameType": "MATCHED_GAME", "gameVersion": "12.8.436.3750", "mapId": 11, "participants": [{"assists": 0, "baronKills": 0, "bountyLevel": 0, "challenges": {"12AssistStreakCount": 0, "abilityUses": 124, "acesBefore15Minutes": 0, "alliedJungleMonsterKills": 4, "baronTakedowns": 0, "blastConeOppositeOpponentCount": 0, "bountyGold": 0, "buffsStolen": 0, "completeSupportQuestInTime": 0, "controlWardTimeCoverageInRiverOrEnemyHalf": 0.011829054341428445, "controlWardsPlaced": 1, "damagePerMinute": 228.82215172572938, "damageTakenOnTeamPercentage": 0.16213730223855422, "dancedWithRiftHerald": 0, "deathsByEnemyChamps": 6, "dodgeSkillShotsSmallWindow": 5, "doubleAces": 0, "dragonTakedowns": 0, "earlyLaningPhaseGoldExpAdvantage": 0, "effectiveHealAndShielding": 0, "elderDragonKillsWithOpposingSoul": 0, "elderDragonMultikills": 0, "enemyChampionImmobilizations": 4, "enemyJungleMonsterKills": 0, "epicMonsterKillsNearEnemyJungler": 0, "epicMonsterKillsWithin30SecondsOfSpawn": 0, "epicMonsterSteals": 0, "epicMonsterStolenWithoutSmite": 0, "flawlessAces": 0, "fullTeamTakedown": 0, "gameLength": 1286.2753827, "getTakedownsInAllLanesEarlyJungleAsLaner": 0, "goldPerMinute": 298.8211803588924, "hadAfkTeammate": 0, "hadOpenNexus": 0, "immobilizeAndKillWithAlly": 0, "initialBuffCount": 0, "initialCrabCount": 0, "jungleCsBefore10Minutes": 0, "junglerTakedownsNearDamagedEpicMonster": 0, "kTurretsDestroyedBeforePlatesFall": 0, "kda": 0.3333333333333333, "killAfterHiddenWithAlly": 0, "killParticipation": 0.05714285714285714, "killedChampTookFullTeamDamageSurvived": 0, "killsNearEnemyTurret": 1, "killsOnOtherLanesEarlyJungleAsLaner": 0, "killsOnRecentlyHealedByAramPack": 0, "killsUnderOwnTurret": 1, "killsWithHelpFromEpicMonster": 0, "knockEnemyIntoTeamAndKill": 0, "landSkillShotsEarlyGame": 3, "laneMinionsFirst10Minutes": 31, "laningPhaseGoldExpAdvantage": 0, "legendaryCount": 0, "lostAnInhibitor": 0, "maxCsAdvantageOnLaneOpponent": 0, "maxKillDeficit": 0, "maxLevelLeadLaneOpponent": 0, "moreEnemyJungleThanOpponent": -119.20000010728836, "multiKillOneSpell": 0, "multiTurretRiftHeraldCount": 0, "multikills": 0, "multikillsAfterAggressiveFlash": 0, "mythicItemUsed": 6632, "outerTurretExecutesBefore10Minutes": 0, "outnumberedKills": 0, "outnumberedNexusKill": 0, "perfectDragonSoulsTaken": 0, "perfectGame": 0, "pickKillWithAlly": 0, "poroExplosions": 0, "quickCleanse": 0, "quickFirstTurret": 0, "quickSoloKills": 0, "riftHeraldTakedowns": 0, "saveAllyFromDeath": 0, "scuttleCrabKills": 0, "skillshotsDodged": 2, "skillshotsHit": 15, "snowballsHit": 0, "soloBaronKills": 0, "soloKills": 2, "soloTurretsLategame": 1, "stealthWardsPlaced": 3, "survivedSingleDigitHpCount": 0, "survivedThreeImmobilizesInFight": 0, "takedownOnFirstTurret": 0, "takedowns": 2, "takedownsAfterGainingLevelAdvantage": 0, "takedownsBeforeJungleMinionSpawn": 0, "takedownsFirstXMinutes": 2, "takedownsInAlcove": 0, "takedownsInEnemyFountain": 0, "teamBaronKills": 0, "teamDamagePercentage": 0.1540557635098232, "teamElderDragonKills": 0, "teamRiftHeraldKills": 0, "threeWardsOneSweeperCount": 0, "tookLargeDamageSurvived": 0, "turretPlatesTaken": 1, "turretTakedowns": 0, "turretsTakenWithRiftHerald": 0, "twentyMinionsIn3SecondsCount": 0, "unseenRecalls": 0, "visionScoreAdvantageLaneOpponent": -0.5856801271438599, "visionScorePerMinute": 0.38951156281153665, "wardTakedowns": 3, "wardTakedownsBefore20M": 3, "wardsGuarded": 0}, "champExperience": 8809, "champLevel": 12, "championId": 24, "championName": "Jax", "championTransform": 0, "consumablesPurchased": 4, "damageDealtToBuildings": 1109, "damageDealtToObjectives": 1109, "damageDealtToTurrets": 1109, "damageSelfMitigated": 6012, "deaths": 6, "detectorWardsPlaced": 1, "doubleKills": 0, "dragonKills": 0, "eligibleForProgression": true, "firstBloodAssist": false, "firstBloodKill": false, "firstTowerAssist": false, "firstTowerKill": false, "gameEndedInEarlySurrender": false, "gameEndedInSurrender": false, "goldEarned": 6406, "goldSpent": 6325, "individualPosition": "JUNGLE", "inhibitorKills": 0, "inhibitorTakedowns": 0, "inhibitorsLost": 2, "item0": 2033, "item1": 6632, "item2": 3082, "item3": 1027, "item4": 1029, "item5": 3158, "item6": 3340, "itemsPurchased": 20, "killingSprees": 0, "kills": 2, "lane": "TOP", "largestCriticalStrike": 0, "largestKillingSpree": 0, "largestMultiKill": 1, "longestTimeSpentLiving": 272, "magicDamageDealt": 13381, "magicDamageDealtToChampions": 608, "magicDamageTaken": 3989, "neutralMinionsKilled": 4, "nexusKills": 0, "nexusLost": 1, "nexusTakedowns": 0, "objectivesStolen": 0, "objectivesStolenAssists": 0, "participantId": 1, "pentaKills": 0, "perks": {"statPerks": {"defense": 5001, "flex": 5008, "offense": 5005}, "styles": [{"description": "primaryStyle", "selections": [{"perk": 8008, "var1": 11, "var2": 0, "var3": 0}, {"perk": 9111, "var1": 0, "var2": 40, "var3": 0}, {"perk": 9105, "var1": 0, "var2": 0, "var3": 0}, {"perk": 8299, "var1": 145, "var2": 0, "var3": 0}], "style": 8000}, {"description": "subStyle", "selections": [{"perk": 8304, "var1": 10, "var2": 3, "var3": 0}, {"perk": 8352, "var1": 206, "var2": 704, "var3": 202}], "style": 8300}]}, "physicalDamageDealt": 51066, "physicalDamageDealtToChampions": 3566, "physicalDamageTaken": 7622, "profileIcon": 20, "puuid": "4n6VLbg0pk_cueIdBdSBhlzIeg7m7G8fj8VfcI8P9EZQyn3vph468NQBzzemIWDqo0YswFDjXUN08Q", "quadraKills": 0, "riotIdName": "", "riotIdTagline": "", "role": "SOLO", "sightWardsBoughtInGame": 0, "spell1Casts": 27, "spell2Casts": 55, "spell3Casts": 38, "spell4Casts": 4, "summoner1Casts": 5, "summoner1Id": 14, "summoner2Casts": 3, "summoner2Id": 4, "summonerId": "9ekNEleeLU3d84TvbL5vdfPHuGXQT3jPeXEDlzBVukdrf7D4yRO4rNj51A", "summonerLevel": 92, "summonerName": "DEEP IN MISERY", "teamEarlySurrendered": false, "teamId": 100, "teamPosition": "TOP", "timeCCingOthers": 4, "timePlayed": 1286, "totalDamageDealt": 74459, "totalDamageDealtToChampions": 4905, "totalDamageShieldedOnTeammates": 0, "totalDamageTaken": 12082, "totalHeal": 949, "totalHealsOnTeammates": 0, "totalMinionsKilled": 124, "totalTimeCCDealt": 50, "totalTimeSpentDead": 133, "totalUnitsHealed": 1, "tripleKills": 0, "trueDamageDealt": 10011, "trueDamageDealtToChampions": 731, "trueDamageTaken": 470, "turretKills": 0, "turretTakedowns": 0, "turretsLost": 10, "unrealKills": 0, "visionScore": 8, "visionWardsBoughtInGame": 1, "wardsKilled": 3, "wardsPlaced": 4, "win": false}, {"assists": 4, "baronKills": 0, "bountyLevel": 0, "challenges": {"12AssistStreakCount": 0, "abilityUses": 195, "acesBefore15Minutes": 0, "alliedJungleMonsterKills": 77.8000001013279, "baronTakedowns": 0, "blastConeOppositeOpponentCount": 0, "bountyGold": 375, "buffsStolen": 0, "completeSupportQuestInTime": 0, "controlWardTimeCoverageInRiverOrEnemyHalf": 0.10188661383296184, "controlWardsPlaced": 3, "damagePerMinute": 442.36176064753204, "damageTakenOnTeamPercentage": 0.28754615482625484, "dancedWithRiftHerald": 0, "deathsByEnemyChamps": 8, "dodgeSkillShotsSmallWindow": 5, "doubleAces": 0, "dragonTakedowns": 1, "earliestDragonTakedown": 825.3433550999999, "earlyLaningPhaseGoldExpAdvantage": 0, "effectiveHealAndShielding": 0, "elderDragonKillsWithOpposingSoul": 0, "elderDragonMultikills": 0, "enemyChampionImmobilizations": 8, "enemyJungleMonsterKills": 0, "epicMonsterKillsNearEnemyJungler": 0, "epicMonsterKillsWithin30SecondsOfSpawn": 0, "epicMonsterSteals": 0, "epicMonsterStolenWithoutSmite": 0, "flawlessAces": 0, "fullTeamTakedown": 0, "gameLength": 1286.2753827, "goldPerMinute": 393.33398362215274, "hadAfkTeammate": 0, "hadOpenNexus": 0, "highestWardKills": 1, "immobilizeAndKillWithAlly": 3, "initialBuffCount": 2, "initialCrabCount": 0, "jungleCsBefore10Minutes": 56.80000004172325, "junglerKillsEarlyJungle": 0, "junglerTakedownsNearDamagedEpicMonster": 0, "kTurretsDestroyedBeforePlatesFall": 0, "kda": 1, "killAfterHiddenWithAlly": 1, "killParticipation": 0.22857142857142856, "killedChampTookFullTeamDamageSurvived": 0, "killsNearEnemyTurret": 1, "killsOnLanersEarlyJungleAsJungler": 2, "killsOnRecentlyHealedByAramPack": 0, "killsUnderOwnTurret": 1, "killsWithHelpFromEpicMonster": 1, "knockEnemyIntoTeamAndKill": 0, "landSkillShotsEarlyGame": 7, "laneMinionsFirst10Minutes": 9, "laningPhaseGoldExpAdvantage": 0, "legendaryCount": 0, "lostAnInhibitor": 0, "maxCsAdvantageOnLaneOpponent": 16.64999994635582, "maxKillDeficit": 0, "maxLevelLeadLaneOpponent": 1, "moreEnemyJungleThanOpponent": -62.40000006556511, "multiKillOneSpell": 0, "multiTurretRiftHeraldCount": 0, "multikills": 0, "multikillsAfterAggressiveFlash": 0, "mythicItemUsed": 6653, "outerTurretExecutesBefore10Minutes": 0, "outnumberedKills": 1, "outnumberedNexusKill": 0, "perfectDragonSoulsTaken": 0, "perfectGame": 0, "pickKillWithAlly": 8, "poroExplosions": 0, "quickCleanse": 0, "quickFirstTurret": 0, "quickSoloKills": 0, "riftHeraldTakedowns": 0, "saveAllyFromDeath": 0, "scuttleCrabKills": 1, "skillshotsDodged": 20, "skillshotsHit": 26, "snowballsHit": 0, "soloBaronKills": 0, "soloKills": 0, "soloTurretsLategame": 1, "stealthWardsPlaced": 1, "survivedSingleDigitHpCount": 0, "survivedThreeImmobilizesInFight": 0, "takedownOnFirstTurret": 0, "takedowns": 8, "takedownsAfterGainingLevelAdvantage": 0, "takedownsBeforeJungleMinionSpawn": 0, "takedownsFirstXMinutes": 8, "takedownsInAlcove": 0, "takedownsInEnemyFountain": 0, "teamBaronKills": 0, "teamDamagePercentage": 0.29782247160139097, "teamElderDragonKills": 0, "teamRiftHeraldKills": 0, "threeWardsOneSweeperCount": 0, "tookLargeDamageSurvived": 0, "turretPlatesTaken": 0, "turretTakedowns": 0, "turretsTakenWithRiftHerald": 0, "twentyMinionsIn3SecondsCount": 0, "unseenRecalls": 0, "visionScoreAdvantageLaneOpponent": -0.038372933864593506, "visionScorePerMinute": 1.0280688740792476, "wardTakedowns": 5, "wardTakedownsBefore20M": 5, "wardsGuarded": 0}, "champExperience": 7725, "champLevel": 11, "championId": 876, "championName": "Lillia", "championTransform": 0, "consumablesPurchased": 4, "damageDealtToBuildings": 0, "damageDealtToObjectives": 7819, "damageDealtToTurrets": 0, "damageSelfMitigated": 7666, "deaths": 8, "detectorWardsPlaced": 3, "doubleKills": 0, "dragonKills": 1, "eligibleForProgression": true, "firstBloodAssist": false, "firstBloodKill": false, "firstTowerAssist": false, "firstTowerKill": false, "gameEndedInEarlySurrender": false, "gameEndedInSurrender": false, "goldEarned": 8432, "goldSpent": 8050, "individualPosition": "JUNGLE", "inhibitorKills": 0, "inhibitorTakedowns": 0, "inhibitorsLost": 2, "item0": 6653, "item1": 2055, "item2": 3157, "item3": 3020, "item4": 0, "item5": 1082, "item6": 3364, "itemsPurchased": 18, "killingSprees": 0, "kills": 4, "lane": "JUNGLE", "largestCriticalStrike": 0, "largestKillingSpree": 0, "largestMultiKill": 1, "longestTimeSpentLiving": 211, "magicDamageDealt": 74555, "magicDamageDealtToChampions": 7010, "magicDamageTaken": 4826, "neutralMinionsKilled": 97, "nexusKills": 0, "nexusLost": 1, "nexusTakedowns": 0, "objectivesStolen": 0, "objectivesStolenAssists": 0, "participantId": 2, "pentaKills": 0, "perks": {"statPerks": {"defense": 5002, "flex": 5008, "offense": 5008}, "styles": [{"description": "primaryStyle", "selections": [{"perk": 8128, "var1": 608, "var2": 11, "var3": 0}, {"perk": 8126, "var1": 477, "var2": 0, "var3": 0}, {"perk": 8138, "var1": 16, "var2": 0, "var3": 0}, {"perk": 8135, "var1": 270, "var2": 4, "var3": 0}], "style": 8100}, {"description": "subStyle", "selections": [{"perk": 8234, "var1": 9580, "var2": 0, "var3": 0}, {"perk": 8232, "var1": 2, "var2": 0, "var3": 0}], "style": 8200}]}, "physicalDamageDealt": 12172, "physicalDamageDealtToChampions": 540, "physicalDamageTaken": 16141, "profileIcon": 1150, "puuid": "vPALV7WzY-yWXhPd5SGk-XTIurDbsmSfOWFuavqCFVysq5VMG-QZNEp5U3_gB4UUcoBoIOyt6ph_0g", "quadraKills": 0, "riotIdName": "", "riotIdTagline": "", "role": "NONE", "sightWardsBoughtInGame": 0, "spell1Casts": 112, "spell2Casts": 43, "spell3Casts": 34, "spell4Casts": 6, "summoner1Casts": 9, "summoner1Id": 11, "summoner2Casts": 3, "summoner2Id": 4, "summonerId": "Z9b3z3bUdOnY1AX9-U4peBg9oNvghi7K7CBlz7uUuHbP0Vk", "summonerLevel": 177, "summonerName": "puppy boy", "teamEarlySurrendered": false, "teamId": 100, "teamPosition": "JUNGLE", "timeCCingOthers": 20, "timePlayed": 1286, "totalDamageDealt": 112026, "totalDamageDealtToChampions": 9483, "totalDamageShieldedOnTeammates": 0, "totalDamageTaken": 21428, "totalHeal": 8780, "totalHealsOnTeammates": 0, "totalMinionsKilled": 32, "totalTimeCCDealt": 187, "totalTimeSpentDead": 193, "totalUnitsHealed": 1, "tripleKills": 0, "trueDamageDealt": 25298, "trueDamageDealtToChampions": 1932, "trueDamageTaken": 460, "turretKills": 0, "turretTakedowns": 0, "turretsLost": 10, "unrealKills": 0, "visionScore": 22, "visionWardsBoughtInGame": 4, "wardsKilled": 5, "wardsPlaced": 4, "win": false}, {"assists": 1, "baronKills": 0, "bountyLevel": 0, "challenges": {"12AssistStreakCount": 0, "abilityUses": 127, "acesBefore15Minutes": 0, "alliedJungleMonsterKills": 0, "baronTakedowns": 0, "blastConeOppositeOpponentCount": 0, "bountyGold": 0, "buffsStolen": 0, "completeSupportQuestInTime": 0, "controlWardTimeCoverageInRiverOrEnemyHalf": 0.19230611642490852, "controlWardsPlaced": 3, "damagePerMinute": 296.37145191581925, "damageTakenOnTeamPercentage": 0.18797333803935032, "dancedWithRiftHerald": 0, "deathsByEnemyChamps": 8, "dodgeSkillShotsSmallWindow": 5, "doubleAces": 0, "dragonTakedowns": 0, "earlyLaningPhaseGoldExpAdvantage": 0, "effectiveHealAndShielding": 0, "elderDragonKillsWithOpposingSoul": 0, "elderDragonMultikills": 0, "enemyChampionImmobilizations": 11, "enemyJungleMonsterKills": 0, "epicMonsterKillsNearEnemyJungler": 0, "epicMonsterKillsWithin30SecondsOfSpawn": 0, "epicMonsterSteals": 0, "epicMonsterStolenWithoutSmite": 0, "flawlessAces": 0, "fullTeamTakedown": 0, "gameLength": 1286.2753827, "getTakedownsInAllLanesEarlyJungleAsLaner": 0, "goldPerMinute": 309.05460177386556, "hadAfkTeammate": 0, "hadOpenNexus": 0, "immobilizeAndKillWithAlly": 2, "initialBuffCount": 0, "initialCrabCount": 0, "jungleCsBefore10Minutes": 0, "junglerTakedownsNearDamagedEpicMonster": 0, "kTurretsDestroyedBeforePlatesFall": 0, "kda": 0.625, "killAfterHiddenWithAlly": 1, "killParticipation": 0.14285714285714285, "killedChampTookFullTeamDamageSurvived": 0, "killsNearEnemyTurret": 0, "killsOnOtherLanesEarlyJungleAsLaner": 1, "killsOnRecentlyHealedByAramPack": 0, "killsUnderOwnTurret": 0, "killsWithHelpFromEpicMonster": 0, "knockEnemyIntoTeamAndKill": 0, "landSkillShotsEarlyGame": 3, "laneMinionsFirst10Minutes": 73, "laningPhaseGoldExpAdvantage": 0, "legendaryCount": 0, "lostAnInhibitor": 0, "maxCsAdvantageOnLaneOpponent": 2.199999988079071, "maxKillDeficit": 0, "maxLevelLeadLaneOpponent": 0, "moreEnemyJungleThanOpponent": -119.20000010728836, "multiKillOneSpell": 0, "multiTurretRiftHeraldCount": 0, "multikills": 1, "multikillsAfterAggressiveFlash": 0, "mythicItemUsed": 6656, "outerTurretExecutesBefore10Minutes": 0, "outnumberedKills": 0, "outnumberedNexusKill": 0, "perfectDragonSoulsTaken": 0, "perfectGame": 0, "pickKillWithAlly": 5, "poroExplosions": 0, "quickCleanse": 0, "quickFirstTurret": 0, "quickSoloKills": 0, "riftHeraldTakedowns": 0, "saveAllyFromDeath": 0, "scuttleCrabKills": 0, "skillshotsDodged": 19, "skillshotsHit": 18, "snowballsHit": 0, "soloBaronKills": 0, "soloKills": 0, "soloTurretsLategame": 1, "stealthWardsPlaced": 4, "survivedSingleDigitHpCount": 0, "survivedThreeImmobilizesInFight": 0, "takedownOnFirstTurret": 0, "takedowns": 5, "takedownsAfterGainingLevelAdvantage": 0, "takedownsBeforeJungleMinionSpawn": 0, "takedownsFirstXMinutes": 5, "takedownsInAlcove": 0, "takedownsInEnemyFountain": 0, "teamBaronKills": 0, "teamDamagePercentage": 0.1995336988270813, "teamElderDragonKills": 0, "teamRiftHeraldKills": 0, "threeWardsOneSweeperCount": 0, "tookLargeDamageSurvived": 0, "turretPlatesTaken": 0, "turretTakedowns": 0, "turretsTakenWithRiftHerald": 0, "twentyMinionsIn3SecondsCount": 0, "unseenRecalls": 0, "visionScoreAdvantageLaneOpponent": 0.40502750873565674, "visionScorePerMinute": 1.022669771554687, "wardTakedowns": 1, "wardTakedownsBefore20M": 1, "wardsGuarded": 0}, "champExperience": 6764, "champLevel": 10, "championId": 103, "championName": "Ahri", "championTransform": 0, "consumablesPurchased": 4, "damageDealtToBuildings": 0, "damageDealtToObjectives": 0, "damageDealtToTurrets": 0, "damageSelfMitigated": 3564, "deaths": 8, "detectorWardsPlaced": 3, "doubleKills": 1, "dragonKills": 0, "eligibleForProgression": true, "firstBloodAssist": false, "firstBloodKill": false, "firstTowerAssist": false, "firstTowerKill": false, "gameEndedInEarlySurrender": false, "gameEndedInSurrender": false, "goldEarned": 6625, "goldSpent": 6350, "individualPosition": "MIDDLE", "inhibitorKills": 0, "inhibitorTakedowns": 0, "inhibitorsLost": 2, "item0": 6656, "item1": 2420, "item2": 2033, "item3": 3191, "item4": 2055, "item5": 3020, "item6": 3364, "itemsPurchased": 20, "killingSprees": 1, "kills": 4, "lane": "MIDDLE", "largestCriticalStrike": 0, "largestKillingSpree": 2, "largestMultiKill": 2, "longestTimeSpentLiving": 253, "magicDamageDealt": 26016, "magicDamageDealtToChampions": 3578, "magicDamageTaken": 4270, "neutralMinionsKilled": 0, "nexusKills": 0, "nexusLost": 1, "nexusTakedowns": 0, "objectivesStolen": 0, "objectivesStolenAssists": 0, "participantId": 3, "pentaKills": 0, "perks": {"statPerks": {"defense": 5003, "flex": 5008, "offense": 5005}, "styles": [{"description": "primaryStyle", "selections": [{"perk": 8112, "var1": 487, "var2": 0, "var3": 0}, {"perk": 8139, "var1": 323, "var2": 0, "var3": 0}, {"perk": 8136, "var1": 4, "var2": 8, "var3": 0}, {"perk": 8106, "var1": 3, "var2": 0, "var3": 0}], "style": 8100}, {"description": "subStyle", "selections": [{"perk": 8345, "var1": 3, "var2": 0, "var3": 0}, {"perk": 8352, "var1": 188, "var2": 607, "var3": 428}], "style": 8300}]}, "physicalDamageDealt": 11965, "physicalDamageDealtToChampions": 905, "physicalDamageTaken": 8933, "profileIcon": 4027, "puuid": "sZ9mXtRpVdxMfxeJBOXLC2csxtHaDlAz0anLy84BN0f839y19CoveIAWupE8kfOHWz6oTHYf9ajbjw", "quadraKills": 0, "riotIdName": "", "riotIdTagline": "", "role": "DUO", "sightWardsBoughtInGame": 0, "spell1Casts": 46, "spell2Casts": 51, "spell3Casts": 17, "spell4Casts": 13, "summoner1Casts": 3, "summoner1Id": 4, "summoner2Casts": 4, "summoner2Id": 14, "summonerId": "ci5lxqJB5aCjApZj4bhHS3rPI1z4Wxz0EqZ4Xa6JXV3Rbw8", "summonerLevel": 247, "summonerName": "Sarcasm Orgasm", "teamEarlySurrendered": false, "teamId": 100, "teamPosition": "MIDDLE", "timeCCingOthers": 14, "timePlayed": 1286, "totalDamageDealt": 58064, "totalDamageDealtToChampions": 6353, "totalDamageShieldedOnTeammates": 0, "totalDamageTaken": 14008, "totalHeal": 1945, "totalHealsOnTeammates": 0, "totalMinionsKilled": 122, "totalTimeCCDealt": 40, "totalTimeSpentDead": 203, "totalUnitsHealed": 1, "tripleKills": 0, "trueDamageDealt": 20082, "trueDamageDealtToChampions": 1869, "trueDamageTaken": 804, "turretKills": 0, "turretTakedowns": 0, "turretsLost": 10, "unrealKills": 0, "visionScore": 21, "visionWardsBoughtInGame": 4, "wardsKilled": 1, "wardsPlaced": 11, "win": false}, {"assists": 2, "baronKills": 0, "bountyLevel": 0, "challenges": {"12AssistStreakCount": 0, "abilityUses": 133, "acesBefore15Minutes": 0, "alliedJungleMonsterKills": 8.000000029802322, "baronTakedowns": 0, "blastConeOppositeOpponentCount": 0, "bountyGold": 800, "buffsStolen": 0, "completeSupportQuestInTime": 0, "controlWardsPlaced": 1, "damagePerMinute": 340.5929507920762, "damageTakenOnTeamPercentage": 0.1801899067598765, "dancedWithRiftHerald": 0, "deathsByEnemyChamps": 5, "dodgeSkillShotsSmallWindow": 5, "doubleAces": 0, "dragonTakedowns": 0, "earlyLaningPhaseGoldExpAdvantage": 0, "effectiveHealAndShielding": 120, "elderDragonKillsWithOpposingSoul": 0, "elderDragonMultikills": 0, "enemyChampionImmobilizations": 3, "enemyJungleMonsterKills": 0, "epicMonsterKillsNearEnemyJungler": 0, "epicMonsterKillsWithin30SecondsOfSpawn": 0, "epicMonsterSteals": 0, "epicMonsterStolenWithoutSmite": 0, "flawlessAces": 0, "fullTeamTakedown": 0, "gameLength": 1286.2753827, "getTakedownsInAllLanesEarlyJungleAsLaner": 0, "goldPerMinute": 390.7579138311764, "hadAfkTeammate": 0, "hadOpenNexus": 0, "immobilizeAndKillWithAlly": 0, "initialBuffCount": 0, "initialCrabCount": 0, "jungleCsBefore10Minutes": 0, "junglerTakedownsNearDamagedEpicMonster": 0, "kTurretsDestroyedBeforePlatesFall": 0, "kda": 0.8, "killAfterHiddenWithAlly": 0, "killParticipation": 0.11428571428571428, "killedChampTookFullTeamDamageSurvived": 0, "killsNearEnemyTurret": 1, "killsOnOtherLanesEarlyJungleAsLaner": 1, "killsOnRecentlyHealedByAramPack": 0, "killsUnderOwnTurret": 1, "killsWithHelpFromEpicMonster": 0, "knockEnemyIntoTeamAndKill": 0, "landSkillShotsEarlyGame": 7, "laneMinionsFirst10Minutes": 71, "laningPhaseGoldExpAdvantage": 0, "legendaryCount": 0, "lostAnInhibitor": 0, "maxCsAdvantageOnLaneOpponent": 0.19999998807907104, "maxKillDeficit": 0, "maxLevelLeadLaneOpponent": 0, "moreEnemyJungleThanOpponent": -119.20000010728836, "multiKillOneSpell": 0, "multiTurretRiftHeraldCount": 0, "multikills": 0, "multikillsAfterAggressiveFlash": 0, "mythicItemUsed": 6672, "outerTurretExecutesBefore10Minutes": 0, "outnumberedKills": 0, "outnumberedNexusKill": 0, "perfectDragonSoulsTaken": 0, "perfectGame": 0, "pickKillWithAlly": 3, "poroExplosions": 0, "quickCleanse": 0, "quickFirstTurret": 0, "quickSoloKills": 0, "riftHeraldTakedowns": 0, "saveAllyFromDeath": 0, "scuttleCrabKills": 0, "skillshotsDodged": 20, "skillshotsHit": 28, "snowballsHit": 0, "soloBaronKills": 0, "soloKills": 1, "soloTurretsLategame": 1, "stealthWardsPlaced": 3, "survivedSingleDigitHpCount": 0, "survivedThreeImmobilizesInFight": 0, "takedownOnFirstTurret": 0, "takedowns": 4, "takedownsAfterGainingLevelAdvantage": 0, "takedownsBeforeJungleMinionSpawn": 0, "takedownsFirstXMinutes": 3, "takedownsInAlcove": 0, "takedownsInEnemyFountain": 0, "teamBaronKills": 0, "teamDamagePercentage": 0.2293060644898963, "teamElderDragonKills": 0, "teamRiftHeraldKills": 0, "threeWardsOneSweeperCount": 0, "tookLargeDamageSurvived": 0, "turretPlatesTaken": 1, "turretTakedowns": 0, "turretsTakenWithRiftHerald": 0, "twentyMinionsIn3SecondsCount": 0, "unseenRecalls": 0, "visionScoreAdvantageLaneOpponent": -0.41025227308273315, "visionScorePerMinute": 0.4292564985552113, "wardTakedowns": 3, "wardTakedownsBefore20M": 1, "wardsGuarded": 0}, "champExperience": 9326, "champLevel": 12, "championId": 222, "championName": "Jinx", "championTransform": 0, "consumablesPurchased": 5, "damageDealtToBuildings": 974, "damageDealtToObjectives": 974, "damageDealtToTurrets": 974, "damageSelfMitigated": 4253, "deaths": 5, "detectorWardsPlaced": 1, "doubleKills": 0, "dragonKills": 0, "eligibleForProgression": true, "firstBloodAssist": false, "firstBloodKill": false, "firstTowerAssist": false, "firstTowerKill": false, "gameEndedInEarlySurrender": false, "gameEndedInSurrender": false, "goldEarned": 8377, "goldSpent": 8050, "individualPosition": "BOTTOM", "inhibitorKills": 0, "inhibitorTakedowns": 0, "inhibitorsLost": 2, "item0": 6672, "item1": 3094, "item2": 2031, "item3": 2055, "item4": 3006, "item5": 1018, "item6": 3363, "itemsPurchased": 19, "killingSprees": 0, "kills": 2, "lane": "MIDDLE", "largestCriticalStrike": 350, "largestKillingSpree": 0, "largestMultiKill": 1, "longestTimeSpentLiving": 477, "magicDamageDealt": 779, "magicDamageDealtToChampions": 279, "magicDamageTaken": 5034, "neutralMinionsKilled": 8, "nexusKills": 0, "nexusLost": 1, "nexusTakedowns": 0, "objectivesStolen": 0, "objectivesStolenAssists": 0, "participantId": 4, "pentaKills": 0, "perks": {"statPerks": {"defense": 5002, "flex": 5008, "offense": 5005}, "styles": [{"description": "primaryStyle", "selections": [{"perk": 8008, "var1": 14, "var2": 3, "var3": 0}, {"perk": 8009, "var1": 610, "var2": 0, "var3": 0}, {"perk": 9103, "var1": 0, "var2": 0, "var3": 0}, {"perk": 8017, "var1": 283, "var2": 0, "var3": 0}], "style": 8000}, {"description": "subStyle", "selections": [{"perk": 8275, "var1": 5, "var2": 0, "var3": 0}, {"perk": 8236, "var1": 14, "var2": 0, "var3": 0}], "style": 8200}]}, "physicalDamageDealt": 70673, "physicalDamageDealtToChampions": 6750, "physicalDamageTaken": 7469, "profileIcon": 1634, "puuid": "CDPynCM5iJ18TN1yr8lYy8VaXsGt7oNlAnoXeGfUuG5Meu_Nai71zAOG8J6T31njfEI2EvQ-tOMF2g", "quadraKills": 0, "riotIdName": "", "riotIdTagline": "", "role": "DUO", "sightWardsBoughtInGame": 0, "spell1Casts": 93, "spell2Casts": 20, "spell3Casts": 12, "spell4Casts": 8, "summoner1Casts": 3, "summoner1Id": 7, "summoner2Casts": 2, "summoner2Id": 4, "summonerId": "dkBJdBOf2fCA7zeS9JyOJ5z9n-ChY9EH7q3GdLkG-nhipjM", "summonerLevel": 587, "summonerName": "Tos8719", "teamEarlySurrendered": false, "teamId": 100, "teamPosition": "BOTTOM", "timeCCingOthers": 7, "timePlayed": 1286, "totalDamageDealt": 74828, "totalDamageDealtToChampions": 7301, "totalDamageShieldedOnTeammates": 0, "totalDamageTaken": 13428, "totalHeal": 395, "totalHealsOnTeammates": 120, "totalMinionsKilled": 171, "totalTimeCCDealt": 54, "totalTimeSpentDead": 118, "totalUnitsHealed": 2, "tripleKills": 0, "trueDamageDealt": 3375, "trueDamageDealtToChampions": 271, "trueDamageTaken": 923, "turretKills": 0, "turretTakedowns": 0, "turretsLost": 10, "unrealKills": 0, "visionScore": 9, "visionWardsBoughtInGame": 2, "wardsKilled": 3, "wardsPlaced": 4, "win": false}, {"assists": 5, "baronKills": 0, "bountyLevel": 0, "challenges": {"12AssistStreakCount": 0, "abilityUses": 60, "acesBefore15Minutes": 0, "alliedJungleMonsterKills": 0, "baronTakedowns": 0, "blastConeOppositeOpponentCount": 0, "bountyGold": 0, "buffsStolen": 0, "completeSupportQuestInTime": 0, "controlWardTimeCoverageInRiverOrEnemyHalf": 0.4298730842841311, "controlWardsPlaced": 3, "damagePerMinute": 177.1719774708241, "damageTakenOnTeamPercentage": 0.18215329813596412, "dancedWithRiftHerald": 0, "deathsByEnemyChamps": 8, "dodgeSkillShotsSmallWindow": 5, "doubleAces": 0, "dragonTakedowns": 0, "earlyLaningPhaseGoldExpAdvantage": 0, "effectiveHealAndShielding": 665.4912109375, "elderDragonKillsWithOpposingSoul": 0, "elderDragonMultikills": 0, "enemyChampionImmobilizations": 30, "enemyJungleMonsterKills": 0, "epicMonsterKillsNearEnemyJungler": 0, "epicMonsterKillsWithin30SecondsOfSpawn": 0, "epicMonsterSteals": 0, "epicMonsterStolenWithoutSmite": 0, "flawlessAces": 0, "fullTeamTakedown": 0, "gameLength": 1286.2753827, "getTakedownsInAllLanesEarlyJungleAsLaner": 0, "goldPerMinute": 200.6321786864708, "hadAfkTeammate": 0, "hadOpenNexus": 0, "immobilizeAndKillWithAlly": 4, "initialBuffCount": 0, "initialCrabCount": 0, "jungleCsBefore10Minutes": 0, "junglerTakedownsNearDamagedEpicMonster": 0, "kTurretsDestroyedBeforePlatesFall": 0, "kda": 0.625, "killAfterHiddenWithAlly": 2, "killParticipation": 0.14285714285714285, "killedChampTookFullTeamDamageSurvived": 0, "killsNearEnemyTurret": 0, "killsOnOtherLanesEarlyJungleAsLaner": 0, "killsOnRecentlyHealedByAramPack": 0, "killsUnderOwnTurret": 0, "killsWithHelpFromEpicMonster": 0, "knockEnemyIntoTeamAndKill": 4, "landSkillShotsEarlyGame": 11, "laneMinionsFirst10Minutes": 9, "laningPhaseGoldExpAdvantage": 0, "legendaryCount": 0, "lostAnInhibitor": 0, "maxCsAdvantageOnLaneOpponent": 0, "maxKillDeficit": 0, "maxLevelLeadLaneOpponent": 0, "moreEnemyJungleThanOpponent": -119.20000010728836, "multiKillOneSpell": 0, "multiTurretRiftHeraldCount": 0, "multikills": 0, "multikillsAfterAggressiveFlash": 0, "outerTurretExecutesBefore10Minutes": 0, "outnumberedKills": 0, "outnumberedNexusKill": 0, "perfectDragonSoulsTaken": 0, "perfectGame": 0, "pickKillWithAlly": 5, "poroExplosions": 0, "quickCleanse": 0, "quickFirstTurret": 0, "quickSoloKills": 0, "riftHeraldTakedowns": 0, "saveAllyFromDeath": 6, "scuttleCrabKills": 0, "skillshotsDodged": 25, "skillshotsHit": 57, "snowballsHit": 0, "soloBaronKills": 0, "soloKills": 0, "soloTurretsLategame": 1, "stealthWardsPlaced": 9, "survivedSingleDigitHpCount": 0, "survivedThreeImmobilizesInFight": 0, "takedownOnFirstTurret": 0, "takedowns": 5, "takedownsAfterGainingLevelAdvantage": 0, "takedownsBeforeJungleMinionSpawn": 0, "takedownsFirstXMinutes": 5, "takedownsInAlcove": 0, "takedownsInEnemyFountain": 0, "teamBaronKills": 0, "teamDamagePercentage": 0.11928200157180825, "teamElderDragonKills": 0, "teamRiftHeraldKills": 0, "threeWardsOneSweeperCount": 0, "tookLargeDamageSurvived": 0, "turretPlatesTaken": 0, "turretTakedowns": 0, "turretsTakenWithRiftHerald": 0, "twentyMinionsIn3SecondsCount": 0, "unseenRecalls": 0, "visionScoreAdvantageLaneOpponent": 0.6701383590698242, "visionScorePerMinute": 1.2156346602256838, "wardTakedowns": 3, "wardTakedownsBefore20M": 3, "wardsGuarded": 0}, "champExperience": 4541, "champLevel": 8, "championId": 53, "championName": "Blitzcrank", "championTransform": 0, "consumablesPurchased": 5, "damageDealtToBuildings": 0, "damageDealtToObjectives": 0, "damageDealtToTurrets": 0, "damageSelfMitigated": 8688, "deaths": 8, "detectorWardsPlaced": 3, "doubleKills": 0, "dragonKills": 0, "eligibleForProgression": true, "firstBloodAssist": false, "firstBloodKill": false, "firstTowerAssist": false, "firstTowerKill": false, "gameEndedInEarlySurrender": false, "gameEndedInSurrender": false, "goldEarned": 4301, "goldSpent": 4075, "individualPosition": "UTILITY", "inhibitorKills": 0, "inhibitorTakedowns": 0, "inhibitorsLost": 2, "item0": 3117, "item1": 3105, "item2": 3067, "item3": 2031, "item4": 0, "item5": 3859, "item6": 3364, "itemsPurchased": 15, "killingSprees": 0, "kills": 0, "lane": "MIDDLE", "largestCriticalStrike": 0, "largestKillingSpree": 0, "largestMultiKill": 0, "longestTimeSpentLiving": 299, "magicDamageDealt": 2955, "magicDamageDealtToChampions": 2086, "magicDamageTaken": 6636, "neutralMinionsKilled": 0, "nexusKills": 0, "nexusLost": 1, "nexusTakedowns": 0, "objectivesStolen": 0, "objectivesStolenAssists": 0, "participantId": 5, "pentaKills": 0, "perks": {"statPerks": {"defense": 5003, "flex": 5002, "offense": 5007}, "styles": [{"description": "primaryStyle", "selections": [{"perk": 8465, "var1": 725, "var2": 0, "var3": 0}, {"perk": 8463, "var1": 185, "var2": 0, "var3": 0}, {"perk": 8444, "var1": 581, "var2": 0, "var3": 0}, {"perk": 8242, "var1": 64, "var2": 0, "var3": 0}], "style": 8400}, {"description": "subStyle", "selections": [{"perk": 8345, "var1": 3, "var2": 0, "var3": 0}, {"perk": 8347, "var1": 0, "var2": 0, "var3": 0}], "style": 8300}]}, "physicalDamageDealt": 3598, "physicalDamageDealtToChampions": 1461, "physicalDamageTaken": 6510, "profileIcon": 3150, "puuid": "bTenuSCiBSHCzB02XDnJK8WBNKKwPgwigTGI6df1lA6_CbzIR0JYa0NYyN7qa1F6Gks0FqlfQXjR1Q", "quadraKills": 0, "riotIdName": "", "riotIdTagline": "", "role": "SUPPORT", "sightWardsBoughtInGame": 0, "spell1Casts": 18, "spell2Casts": 18, "spell3Casts": 19, "spell4Casts": 5, "summoner1Casts": 3, "summoner1Id": 4, "summoner2Casts": 3, "summoner2Id": 14, "summonerId": "9pBylBi9Izvd1NZQvko5eBhkOjbFwy31X_wQ7a5m1RhnXIgGGxz1kRIrGA", "summonerLevel": 57, "summonerName": "YNO CRANK", "teamEarlySurrendered": false, "teamId": 100, "teamPosition": "UTILITY", "timeCCingOthers": 19, "timePlayed": 1286, "totalDamageDealt": 11050, "totalDamageDealtToChampions": 3798, "totalDamageShieldedOnTeammates": 527, "totalDamageTaken": 13574, "totalHeal": 110, "totalHealsOnTeammates": 137, "totalMinionsKilled": 20, "totalTimeCCDealt": 55, "totalTimeSpentDead": 161, "totalUnitsHealed": 3, "tripleKills": 0, "trueDamageDealt": 4496, "trueDamageDealtToChampions": 250, "trueDamageTaken": 427, "turretKills": 0, "turretTakedowns": 0, "turretsLost": 10, "unrealKills": 0, "visionScore": 26, "visionWardsBoughtInGame": 3, "wardsKilled": 3, "wardsPlaced": 12, "win": false}, {"assists": 5, "baronKills": 0, "bountyLevel": 5, "challenges": {"12AssistStreakCount": 0, "abilityUses": 128, "acesBefore15Minutes": 0, "alliedJungleMonsterKills": 0, "baronTakedowns": 0, "blastConeOppositeOpponentCount": 0, "bountyGold": 0, "buffsStolen": 1, "completeSupportQuestInTime": 0, "controlWardTimeCoverageInRiverOrEnemyHalf": 0.14045876110974098, "controlWardsPlaced": 1, "damagePerMinute": 556.8518938059749, "damageTakenOnTeamPercentage": 0.16553872236784395, "dancedWithRiftHerald": 0, "deathsByEnemyChamps": 2, "dodgeSkillShotsSmallWindow": 5, "doubleAces": 0, "dragonTakedowns": 0, "earlyLaningPhaseGoldExpAdvantage": 0, "effectiveHealAndShielding": 0, "elderDragonKillsWithOpposingSoul": 0, "elderDragonMultikills": 0, "enemyChampionImmobilizations": 1, "enemyJungleMonsterKills": 4, "epicMonsterKillsNearEnemyJungler": 0, "epicMonsterKillsWithin30SecondsOfSpawn": 0, "epicMonsterSteals": 0, "epicMonsterStolenWithoutSmite": 0, "firstTurretKilledTime": 809.9673709, "flawlessAces": 0, "fullTeamTakedown": 1, "gameLength": 1286.2753827, "getTakedownsInAllLanesEarlyJungleAsLaner": 0, "goldPerMinute": 527.0355634660084, "hadAfkTeammate": 0, "hadOpenNexus": 0, "immobilizeAndKillWithAlly": 1, "initialBuffCount": 0, "initialCrabCount": 0, "jungleCsBefore10Minutes": 0, "junglerTakedownsNearDamagedEpicMonster": 0, "kTurretsDestroyedBeforePlatesFall": 0, "kda": 6, "killAfterHiddenWithAlly": 0, "killParticipation": 1, "killedChampTookFullTeamDamageSurvived": 0, "killsNearEnemyTurret": 4, "killsOnOtherLanesEarlyJungleAsLaner": 0, "killsOnRecentlyHealedByAramPack": 0, "killsUnderOwnTurret": 1, "killsWithHelpFromEpicMonster": 0, "knockEnemyIntoTeamAndKill": 1, "landSkillShotsEarlyGame": 0, "laneMinionsFirst10Minutes": 79, "laningPhaseGoldExpAdvantage": 1, "legendaryCount": 0, "lostAnInhibitor": 0, "maxCsAdvantageOnLaneOpponent": 80, "maxKillDeficit": 0, "maxLevelLeadLaneOpponent": 2, "moreEnemyJungleThanOpponent": -115.05000004172325, "multiKillOneSpell": 0, "multiTurretRiftHeraldCount": 1, "multikills": 0, "multikillsAfterAggressiveFlash": 0, "mythicItemUsed": 6671, "outerTurretExecutesBefore10Minutes": 0, "outnumberedKills": 0, "outnumberedNexusKill": 0, "perfectDragonSoulsTaken": 0, "perfectGame": 0, "pickKillWithAlly": 5, "poroExplosions": 0, "quickCleanse": 0, "quickFirstTurret": 1, "quickSoloKills": 0, "riftHeraldTakedowns": 0, "saveAllyFromDeath": 0, "scuttleCrabKills": 0, "skillshotsDodged": 1, "skillshotsHit": 8, "snowballsHit": 0, "soloBaronKills": 0, "soloKills": 3, "soloTurretsLategame": 1, "stealthWardsPlaced": 4, "survivedSingleDigitHpCount": 0, "survivedThreeImmobilizesInFight": 0, "takedownOnFirstTurret": 0, "takedowns": 12, "takedownsAfterGainingLevelAdvantage": 0, "takedownsBeforeJungleMinionSpawn": 0, "takedownsFirstXMinutes": 5, "takedownsInAlcove": 0, "takedownsInEnemyFountain": 1, "teamBaronKills": 0, "teamDamagePercentage": 0.20344443544722282, "teamElderDragonKills": 0, "teamRiftHeraldKills": 1, "threeWardsOneSweeperCount": 0, "tookLargeDamageSurvived": 0, "turretPlatesTaken": 4, "turretTakedowns": 7, "turretsTakenWithRiftHerald": 10, "twentyMinionsIn3SecondsCount": 0, "unseenRecalls": 0, "visionScoreAdvantageLaneOpponent": 1.4135940074920654, "visionScorePerMinute": 0.9401227752593748, "wardTakedowns": 3, "wardTakedownsBefore20M": 2, "wardsGuarded": 0}, "champExperience": 10674, "champLevel": 13, "championId": 236, "championName": "Lucian", "championTransform": 0, "consumablesPurchased": 4, "damageDealtToBuildings": 9768, "damageDealtToObjectives": 9768, "damageDealtToTurrets": 9768, "damageSelfMitigated": 3370, "deaths": 2, "detectorWardsPlaced": 1, "doubleKills": 0, "dragonKills": 0, "eligibleForProgression": true, "firstBloodAssist": false, "firstBloodKill": true, "firstTowerAssist": false, "firstTowerKill": false, "gameEndedInEarlySurrender": false, "gameEndedInSurrender": false, "goldEarned": 11298, "goldSpent": 9475, "individualPosition": "TOP", "inhibitorKills": 1, "inhibitorTakedowns": 2, "inhibitorsLost": 0, "item0": 6671, "item1": 3006, "item2": 3508, "item3": 3035, "item4": 1055, "item5": 1036, "item6": 3363, "itemsPurchased": 17, "killingSprees": 1, "kills": 7, "lane": "TOP", "largestCriticalStrike": 423, "largestKillingSpree": 5, "largestMultiKill": 1, "longestTimeSpentLiving": 185, "magicDamageDealt": 5116, "magicDamageDealtToChampions": 1511, "magicDamageTaken": 1190, "neutralMinionsKilled": 4, "nexusKills": 0, "nexusLost": 0, "nexusTakedowns": 1, "objectivesStolen": 0, "objectivesStolenAssists": 0, "participantId": 6, "pentaKills": 0, "perks": {"statPerks": {"defense": 5002, "flex": 5008, "offense": 5005}, "styles": [{"description": "primaryStyle", "selections": [{"perk": 8005, "var1": 453, "var2": 308, "var3": 145}, {"perk": 8009, "var1": 1626, "var2": 0, "var3": 0}, {"perk": 9103, "var1": 18, "var2": 0, "var3": 0}, {"perk": 8014, "var1": 292, "var2": 0, "var3": 0}], "style": 8000}, {"description": "subStyle", "selections": [{"perk": 8304, "var1": 9, "var2": 4, "var3": 5}, {"perk": 8345, "var1": 3, "var2": 0, "var3": 0}], "style": 8300}]}, "physicalDamageDealt": 101922, "physicalDamageDealtToChampions": 9959, "physicalDamageTaken": 6187, "profileIcon": 23, "puuid": "hg-weySh2vJHoAZ-Lpo40D-YCAJtUcEwI_fJ0D-5nnx8-bvcyiOvENLZhVd1msfhUdWf7EDnpqYhjg", "quadraKills": 0, "riotIdName": "", "riotIdTagline": "", "role": "SOLO", "sightWardsBoughtInGame": 0, "spell1Casts": 53, "spell2Casts": 37, "spell3Casts": 28, "spell4Casts": 10, "summoner1Casts": 4, "summoner1Id": 4, "summoner2Casts": 5, "summoner2Id": 14, "summonerId": "t2AvdB07DJoTPMUIzp5bQsPyFENirSOlFX0GJLrGKJsk4LzLNTtKYkyu5g", "summonerLevel": 111, "summonerName": "only for myself", "teamEarlySurrendered": false, "teamId": 200, "teamPosition": "TOP", "timeCCingOthers": 0, "timePlayed": 1286, "totalDamageDealt": 107504, "totalDamageDealtToChampions": 11937, "totalDamageShieldedOnTeammates": 0, "totalDamageTaken": 7938, "totalHeal": 148, "totalHealsOnTeammates": 0, "totalMinionsKilled": 179, "totalTimeCCDealt": 1, "totalTimeSpentDead": 20, "totalUnitsHealed": 1, "tripleKills": 0, "trueDamageDealt": 466, "trueDamageDealtToChampions": 466, "trueDamageTaken": 560, "turretKills": 5, "turretTakedowns": 7, "turretsLost": 0, "unrealKills": 0, "visionScore": 20, "visionWardsBoughtInGame": 1, "wardsKilled": 3, "wardsPlaced": 8, "win": true}, {"assists": 6, "baronKills": 0, "bountyLevel": 4, "challenges": {"12AssistStreakCount": 0, "abilityUses": 567, "acesBefore15Minutes": 0, "alliedJungleMonsterKills": 84.50000017881393, "baronTakedowns": 0, "blastConeOppositeOpponentCount": 0, "bountyGold": 0, "buffsStolen": 1, "completeSupportQuestInTime": 0, "controlWardTimeCoverageInRiverOrEnemyHalf": 0.0910057940736487, "controlWardsPlaced": 2, "damagePerMinute": 407.94739786673216, "damageTakenOnTeamPercentage": 0.33194688854181864, "dancedWithRiftHerald": 0, "deathsByEnemyChamps": 3, "dodgeSkillShotsSmallWindow": 5, "doubleAces": 0, "dragonTakedowns": 0, "earlyLaningPhaseGoldExpAdvantage": 0, "effectiveHealAndShielding": 0, "elderDragonKillsWithOpposingSoul": 0, "elderDragonMultikills": 0, "enemyChampionImmobilizations": 3, "enemyJungleMonsterKills": 7.4000000059604645, "epicMonsterKillsNearEnemyJungler": 0, "epicMonsterKillsWithin30SecondsOfSpawn": 0, "epicMonsterSteals": 0, "epicMonsterStolenWithoutSmite": 0, "firstTurretKilledTime": 809.9673709, "flawlessAces": 0, "fullTeamTakedown": 1, "gameLength": 1286.2753827, "goldPerMinute": 468.0817796953241, "hadAfkTeammate": 0, "hadOpenNexus": 0, "immobilizeAndKillWithAlly": 1, "initialBuffCount": 2, "initialCrabCount": 1, "jungleCsBefore10Minutes": 56.15000009536743, "junglerKillsEarlyJungle": 0, "junglerTakedownsNearDamagedEpicMonster": 0, "kTurretsDestroyedBeforePlatesFall": 0, "kda": 4.666666666666667, "killAfterHiddenWithAlly": 1, "killParticipation": 1.1666666666666667, "killedChampTookFullTeamDamageSurvived": 0, "killsNearEnemyTurret": 1, "killsOnLanersEarlyJungleAsJungler": 3, "killsOnRecentlyHealedByAramPack": 0, "killsUnderOwnTurret": 1, "killsWithHelpFromEpicMonster": 0, "knockEnemyIntoTeamAndKill": 0, "landSkillShotsEarlyGame": 4, "laneMinionsFirst10Minutes": 2, "laningPhaseGoldExpAdvantage": 0, "legendaryCount": 1, "lostAnInhibitor": 0, "maxCsAdvantageOnLaneOpponent": 16.000000029802322, "maxKillDeficit": 0, "maxLevelLeadLaneOpponent": 3, "moreEnemyJungleThanOpponent": -58.89999994635582, "multiKillOneSpell": 0, "multiTurretRiftHeraldCount": 1, "multikills": 1, "multikillsAfterAggressiveFlash": 0, "mythicItemUsed": 3152, "outerTurretExecutesBefore10Minutes": 0, "outnumberedKills": 0, "outnumberedNexusKill": 0, "perfectDragonSoulsTaken": 0, "perfectGame": 0, "pickKillWithAlly": 11, "poroExplosions": 0, "quickCleanse": 0, "quickFirstTurret": 1, "quickSoloKills": 1, "riftHeraldTakedowns": 1, "saveAllyFromDeath": 0, "scuttleCrabKills": 3, "skillshotsDodged": 7, "skillshotsHit": 20, "snowballsHit": 0, "soloBaronKills": 0, "soloKills": 2, "soloTurretsLategame": 1, "stealthWardsPlaced": 7, "survivedSingleDigitHpCount": 0, "survivedThreeImmobilizesInFight": 2, "takedownOnFirstTurret": 0, "takedowns": 14, "takedownsAfterGainingLevelAdvantage": 1, "takedownsBeforeJungleMinionSpawn": 0, "takedownsFirstXMinutes": 9, "takedownsInAlcove": 1, "takedownsInEnemyFountain": 0, "teamBaronKills": 0, "teamDamagePercentage": 0.14904255327912905, "teamElderDragonKills": 0, "teamRiftHeraldKills": 1, "threeWardsOneSweeperCount": 0, "tookLargeDamageSurvived": 0, "turretPlatesTaken": 0, "turretTakedowns": 3, "turretsTakenWithRiftHerald": 10, "twentyMinionsIn3SecondsCount": 0, "unseenRecalls": 0, "visionScoreAdvantageLaneOpponent": 0.039904236793518066, "visionScorePerMinute": 1.0690931206000736, "wardTakedowns": 2, "wardTakedownsBefore20M": 2, "wardsGuarded": 0}, "champExperience": 10550, "champLevel": 13, "championId": 28, "championName": "Evelynn", "championTransform": 0, "consumablesPurchased": 2, "damageDealtToBuildings": 1578, "damageDealtToObjectives": 12569, "damageDealtToTurrets": 1578, "damageSelfMitigated": 7486, "deaths": 3, "detectorWardsPlaced": 2, "doubleKills": 1, "dragonKills": 0, "eligibleForProgression": true, "firstBloodAssist": false, "firstBloodKill": false, "firstTowerAssist": false, "firstTowerKill": false, "gameEndedInEarlySurrender": false, "gameEndedInSurrender": false, "goldEarned": 10034, "goldSpent": 8000, "individualPosition": "JUNGLE", "inhibitorKills": 0, "inhibitorTakedowns": 0, "inhibitorsLost": 0, "item0": 0, "item1": 3152, "item2": 2031, "item3": 1082, "item4": 3100, "item5": 3020, "item6": 3363, "itemsPurchased": 17, "killingSprees": 2, "kills": 8, "lane": "JUNGLE", "largestCriticalStrike": 0, "largestKillingSpree": 4, "largestMultiKill": 2, "longestTimeSpentLiving": 480, "magicDamageDealt": 103710, "magicDamageDealtToChampions": 7956, "magicDamageTaken": 5141, "neutralMinionsKilled": 115, "nexusKills": 0, "nexusLost": 0, "nexusTakedowns": 1, "objectivesStolen": 0, "objectivesStolenAssists": 0, "participantId": 7, "pentaKills": 0, "perks": {"statPerks": {"defense": 5003, "flex": 5008, "offense": 5008}, "styles": [{"description": "primaryStyle", "selections": [{"perk": 8112, "var1": 573, "var2": 0, "var3": 0}, {"perk": 8143, "var1": 340, "var2": 0, "var3": 0}, {"perk": 8138, "var1": 30, "var2": 0, "var3": 0}, {"perk": 8105, "var1": 13, "var2": 5, "var3": 0}], "style": 8100}, {"description": "subStyle", "selections": [{"perk": 8304, "var1": 8, "var2": 1, "var3": 5}, {"perk": 8347, "var1": 0, "var2": 0, "var3": 0}], "style": 8300}]}, "physicalDamageDealt": 9604, "physicalDamageDealtToChampions": 148, "physicalDamageTaken": 9367, "profileIcon": 588, "puuid": "ylH3YxKCmkgWy3X_u-bGPNy4cX9oF9KWMLHrTtA9vgTYC-6KSlnLXJ3YPNLkAMIGn2c79_YS7dyLxQ", "quadraKills": 0, "riotIdName": "", "riotIdTagline": "", "role": "NONE", "sightWardsBoughtInGame": 0, "spell1Casts": 440, "spell2Casts": 30, "spell3Casts": 91, "spell4Casts": 6, "summoner1Casts": 3, "summoner1Id": 4, "summoner2Casts": 14, "summoner2Id": 11, "summonerId": "qJN4WiKvFpewnqA0M7qUsvvc44NEydzj6mCPxyj4auzpRnk", "summonerLevel": 547, "summonerName": "c2 meteos", "teamEarlySurrendered": false, "teamId": 200, "teamPosition": "JUNGLE", "timeCCingOthers": 5, "timePlayed": 1286, "totalDamageDealt": 121581, "totalDamageDealtToChampions": 8745, "totalDamageShieldedOnTeammates": 0, "totalDamageTaken": 15918, "totalHeal": 6388, "totalHealsOnTeammates": 0, "totalMinionsKilled": 25, "totalTimeCCDealt": 108, "totalTimeSpentDead": 72, "totalUnitsHealed": 1, "tripleKills": 0, "trueDamageDealt": 8266, "trueDamageDealtToChampions": 640, "trueDamageTaken": 1410, "turretKills": 2, "turretTakedowns": 3, "turretsLost": 0, "unrealKills": 0, "visionScore": 22, "visionWardsBoughtInGame": 2, "wardsKilled": 2, "wardsPlaced": 10, "win": true}, {"assists": 5, "baronKills": 0, "bountyLevel": 3, "challenges": {"12AssistStreakCount": 0, "abilityUses": 96, "acesBefore15Minutes": 0, "alliedJungleMonsterKills": 12, "baronTakedowns": 0, "blastConeOppositeOpponentCount": 0, "bountyGold": 0, "buffsStolen": 0, "completeSupportQuestInTime": 0, "controlWardTimeCoverageInRiverOrEnemyHalf": 0.1690770136978693, "controlWardsPlaced": 2, "damagePerMinute": 1083.227530426094, "damageTakenOnTeamPercentage": 0.21401932726581865, "dancedWithRiftHerald": 0, "deathsByEnemyChamps": 2, "dodgeSkillShotsSmallWindow": 5, "doubleAces": 0, "dragonTakedowns": 2, "earliestDragonTakedown": 825.3433550999999, "earlyLaningPhaseGoldExpAdvantage": 1, "effectiveHealAndShielding": 0, "elderDragonKillsWithOpposingSoul": 0, "elderDragonMultikills": 0, "enemyChampionImmobilizations": 0, "enemyJungleMonsterKills": 9.300000011920929, "epicMonsterKillsNearEnemyJungler": 0, "epicMonsterKillsWithin30SecondsOfSpawn": 0, "epicMonsterSteals": 0, "epicMonsterStolenWithoutSmite": 0, "fastestLegendary": 901.2016008999999, "firstTurretKilledTime": 809.9673709, "flawlessAces": 0, "fullTeamTakedown": 1, "gameLength": 1286.2753827, "getTakedownsInAllLanesEarlyJungleAsLaner": 0, "goldPerMinute": 682.1725348108461, "hadAfkTeammate": 0, "hadOpenNexus": 0, "highestChampionDamage": 1, "highestCrowdControlScore": 1, "immobilizeAndKillWithAlly": 0, "initialBuffCount": 0, "initialCrabCount": 0, "jungleCsBefore10Minutes": 0.800000011920929, "junglerTakedownsNearDamagedEpicMonster": 0, "kTurretsDestroyedBeforePlatesFall": 1, "kda": 11, "killAfterHiddenWithAlly": 0, "killParticipation": 1.8333333333333333, "killedChampTookFullTeamDamageSurvived": 0, "killsNearEnemyTurret": 6, "killsOnOtherLanesEarlyJungleAsLaner": 0, "killsOnRecentlyHealedByAramPack": 0, "killsUnderOwnTurret": 0, "killsWithHelpFromEpicMonster": 0, "knockEnemyIntoTeamAndKill": 0, "landSkillShotsEarlyGame": 5, "laneMinionsFirst10Minutes": 90, "laningPhaseGoldExpAdvantage": 1, "legendaryCount": 2, "lostAnInhibitor": 0, "maxCsAdvantageOnLaneOpponent": 84.30000001192093, "maxKillDeficit": 0, "maxLevelLeadLaneOpponent": 4, "moreEnemyJungleThanOpponent": -114.25000002980232, "multiKillOneSpell": 0, "multiTurretRiftHeraldCount": 1, "multikills": 3, "multikillsAfterAggressiveFlash": 0, "mythicItemUsed": 6692, "outerTurretExecutesBefore10Minutes": 0, "outnumberedKills": 4, "outnumberedNexusKill": 0, "perfectDragonSoulsTaken": 0, "perfectGame": 0, "pickKillWithAlly": 15, "poroExplosions": 0, "quickCleanse": 0, "quickFirstTurret": 1, "quickSoloKills": 2, "riftHeraldTakedowns": 0, "saveAllyFromDeath": 0, "scuttleCrabKills": 0, "skillshotsDodged": 10, "skillshotsHit": 15, "snowballsHit": 0, "soloBaronKills": 0, "soloKills": 5, "soloTurretsLategame": 1, "stealthWardsPlaced": 3, "survivedSingleDigitHpCount": 0, "survivedThreeImmobilizesInFight": 4, "takedownOnFirstTurret": 1, "takedowns": 22, "takedownsAfterGainingLevelAdvantage": 0, "takedownsBeforeJungleMinionSpawn": 0, "takedownsFirstXMinutes": 10, "takedownsInAlcove": 0, "takedownsInEnemyFountain": 0, "teamBaronKills": 0, "teamDamagePercentage": 0.3957544471694163, "teamElderDragonKills": 0, "teamRiftHeraldKills": 1, "threeWardsOneSweeperCount": 0, "tookLargeDamageSurvived": 0, "turretPlatesTaken": 6, "turretTakedowns": 6, "turretsTakenWithRiftHerald": 10, "twentyMinionsIn3SecondsCount": 0, "unseenRecalls": 0, "visionScoreAdvantageLaneOpponent": -0.28827011585235596, "visionScorePerMinute": 0.7278646184633419, "wardTakedowns": 2, "wardTakedownsBefore20M": 2, "wardsGuarded": 0}, "champExperience": 12504, "champLevel": 14, "championId": 104, "championName": "Graves", "championTransform": 0, "consumablesPurchased": 5, "damageDealtToBuildings": 9437, "damageDealtToObjectives": 15479, "damageDealtToTurrets": 9437, "damageSelfMitigated": 9503, "deaths": 2, "detectorWardsPlaced": 2, "doubleKills": 2, "dragonKills": 1, "eligibleForProgression": true, "firstBloodAssist": false, "firstBloodKill": false, "firstTowerAssist": false, "firstTowerKill": true, "gameEndedInEarlySurrender": false, "gameEndedInSurrender": false, "goldEarned": 14624, "goldSpent": 12200, "individualPosition": "MIDDLE", "inhibitorKills": 0, "inhibitorTakedowns": 2, "inhibitorsLost": 0, "item0": 6692, "item1": 3156, "item2": 6676, "item3": 3111, "item4": 3035, "item5": 1036, "item6": 3363, "itemsPurchased": 21, "killingSprees": 3, "kills": 17, "lane": "MIDDLE", "largestCriticalStrike": 365, "largestKillingSpree": 12, "largestMultiKill": 3, "longestTimeSpentLiving": 830, "magicDamageDealt": 657, "magicDamageDealtToChampions": 657, "magicDamageTaken": 2599, "neutralMinionsKilled": 25, "nexusKills": 1, "nexusLost": 0, "nexusTakedowns": 1, "objectivesStolen": 0, "objectivesStolenAssists": 0, "participantId": 8, "pentaKills": 0, "perks": {"statPerks": {"defense": 5003, "flex": 5008, "offense": 5005}, "styles": [{"description": "primaryStyle", "selections": [{"perk": 8112, "var1": 1238, "var2": 0, "var3": 0}, {"perk": 8143, "var1": 773, "var2": 0, "var3": 0}, {"perk": 8138, "var1": 18, "var2": 0, "var3": 0}, {"perk": 8105, "var1": 13, "var2": 5, "var3": 0}], "style": 8100}, {"description": "subStyle", "selections": [{"perk": 9104, "var1": 8, "var2": 40, "var3": 0}, {"perk": 8014, "var1": 590, "var2": 0, "var3": 0}], "style": 8000}]}, "physicalDamageDealt": 138374, "physicalDamageDealtToChampions": 20584, "physicalDamageTaken": 6174, "profileIcon": 3377, "puuid": "iCY13jSZ3RTBcwsKGFV5VogSuneSxeAgc46b0dJyOm2JfVq-6ia0PVOgPOXLFMO2tabELO7wz5hLeA", "quadraKills": 0, "riotIdName": "", "riotIdTagline": "", "role": "SOLO", "sightWardsBoughtInGame": 0, "spell1Casts": 50, "spell2Casts": 17, "spell3Casts": 24, "spell4Casts": 5, "summoner1Casts": 5, "summoner1Id": 14, "summoner2Casts": 3, "summoner2Id": 4, "summonerId": "ZzdWNma2HRVni1jIFbFkI-YQztzAoIGwtJ4qMP0R_xCGd4o", "summonerLevel": 173, "summonerName": "perry1", "teamEarlySurrendered": false, "teamId": 200, "teamPosition": "MIDDLE", "timeCCingOthers": 19, "timePlayed": 1286, "totalDamageDealt": 144340, "totalDamageDealtToChampions": 23222, "totalDamageShieldedOnTeammates": 0, "totalDamageTaken": 10263, "totalHeal": 0, "totalHealsOnTeammates": 0, "totalMinionsKilled": 177, "totalTimeCCDealt": 289, "totalTimeSpentDead": 55, "totalUnitsHealed": 0, "tripleKills": 1, "trueDamageDealt": 5308, "trueDamageDealtToChampions": 1980, "trueDamageTaken": 1489, "turretKills": 2, "turretTakedowns": 6, "turretsLost": 0, "unrealKills": 0, "visionScore": 15, "visionWardsBoughtInGame": 2, "wardsKilled": 2, "wardsPlaced": 8, "win": true}, {"assists": 11, "baronKills": 0, "bountyLevel": 2, "challenges": {"12AssistStreakCount": 0, "abilityUses": 145, "acesBefore15Minutes": 0, "alliedJungleMonsterKills": 0, "baronTakedowns": 0, "blastConeOppositeOpponentCount": 0, "bountyGold": 0, "buffsStolen": 0, "completeSupportQuestInTime": 0, "controlWardTimeCoverageInRiverOrEnemyHalf": 0.6837005251192856, "controlWardsPlaced": 1, "damagePerMinute": 275.4930829503195, "damageTakenOnTeamPercentage": 0.10859896031862419, "dancedWithRiftHerald": 0, "deathsByEnemyChamps": 1, "dodgeSkillShotsSmallWindow": 5, "doubleAces": 0, "dragonTakedowns": 0, "effectiveHealAndShielding": 4309.05810546875, "elderDragonKillsWithOpposingSoul": 0, "elderDragonMultikills": 0, "enemyChampionImmobilizations": 6, "enemyJungleMonsterKills": 1, "epicMonsterKillsNearEnemyJungler": 0, "epicMonsterKillsWithin30SecondsOfSpawn": 0, "epicMonsterSteals": 0, "epicMonsterStolenWithoutSmite": 0, "firstTurretKilledTime": 809.9673709, "flawlessAces": 0, "fullTeamTakedown": 1, "gameLength": 1286.2753827, "getTakedownsInAllLanesEarlyJungleAsLaner": 0, "goldPerMinute": 364.06112378918425, "hadAfkTeammate": 0, "hadOpenNexus": 0, "immobilizeAndKillWithAlly": 2, "initialBuffCount": 0, "initialCrabCount": 1, "jungleCsBefore10Minutes": 4, "junglerTakedownsNearDamagedEpicMonster": 0, "kTurretsDestroyedBeforePlatesFall": 0, "kda": 13, "killAfterHiddenWithAlly": 1, "killParticipation": 1.0833333333333333, "killedChampTookFullTeamDamageSurvived": 0, "killsNearEnemyTurret": 1, "killsOnOtherLanesEarlyJungleAsLaner": 0, "killsOnRecentlyHealedByAramPack": 0, "killsUnderOwnTurret": 0, "killsWithHelpFromEpicMonster": 0, "knockEnemyIntoTeamAndKill": 0, "landSkillShotsEarlyGame": 1, "laneMinionsFirst10Minutes": 73, "legendaryCount": 0, "lostAnInhibitor": 0, "maxKillDeficit": 0, "moreEnemyJungleThanOpponent": -111.05000004172325, "multiKillOneSpell": 0, "multiTurretRiftHeraldCount": 1, "multikills": 0, "multikillsAfterAggressiveFlash": 0, "mythicItemUsed": 6653, "outerTurretExecutesBefore10Minutes": 0, "outnumberedKills": 0, "outnumberedNexusKill": 0, "perfectDragonSoulsTaken": 0, "perfectGame": 0, "pickKillWithAlly": 9, "poroExplosions": 0, "quickCleanse": 0, "quickFirstTurret": 1, "quickSoloKills": 0, "riftHeraldTakedowns": 0, "saveAllyFromDeath": 3, "scuttleCrabKills": 1, "skillshotsDodged": 1, "skillshotsHit": 4, "snowballsHit": 0, "soloBaronKills": 0, "soloKills": 0, "soloTurretsLategame": 1, "stealthWardsPlaced": 7, "survivedSingleDigitHpCount": 0, "survivedThreeImmobilizesInFight": 2, "takedownOnFirstTurret": 0, "takedowns": 13, "takedownsAfterGainingLevelAdvantage": 0, "takedownsBeforeJungleMinionSpawn": 0, "takedownsFirstXMinutes": 2, "takedownsInAlcove": 0, "takedownsInEnemyFountain": 0, "teamBaronKills": 0, "teamDamagePercentage": 0.10065070327294504, "teamElderDragonKills": 0, "teamRiftHeraldKills": 1, "threeWardsOneSweeperCount": 0, "tookLargeDamageSurvived": 0, "turretPlatesTaken": 1, "turretTakedowns": 4, "turretsTakenWithRiftHerald": 10, "twentyMinionsIn3SecondsCount": 0, "unseenRecalls": 0, "visionScorePerMinute": 1.0982521355643458, "wardTakedowns": 2, "wardTakedownsBefore20M": 2, "wardsGuarded": 0}, "champExperience": 8849, "champLevel": 12, "championId": 147, "championName": "Seraphine", "championTransform": 0, "consumablesPurchased": 4, "damageDealtToBuildings": 1766, "damageDealtToObjectives": 1766, "damageDealtToTurrets": 1766, "damageSelfMitigated": 1881, "deaths": 1, "detectorWardsPlaced": 1, "doubleKills": 0, "dragonKills": 0, "eligibleForProgression": true, "firstBloodAssist": false, "firstBloodKill": false, "firstTowerAssist": false, "firstTowerKill": false, "gameEndedInEarlySurrender": false, "gameEndedInSurrender": false, "goldEarned": 7804, "goldSpent": 6550, "individualPosition": "BOTTOM", "inhibitorKills": 1, "inhibitorTakedowns": 2, "inhibitorsLost": 0, "item0": 1056, "item1": 3158, "item2": 6653, "item3": 3108, "item4": 3113, "item5": 0, "item6": 3340, "itemsPurchased": 16, "killingSprees": 1, "kills": 2, "lane": "BOTTOM", "largestCriticalStrike": 0, "largestKillingSpree": 2, "largestMultiKill": 1, "longestTimeSpentLiving": 462, "magicDamageDealt": 51643, "magicDamageDealtToChampions": 5086, "magicDamageTaken": 1221, "neutralMinionsKilled": 5, "nexusKills": 0, "nexusLost": 0, "nexusTakedowns": 1, "objectivesStolen": 0, "objectivesStolenAssists": 0, "participantId": 9, "pentaKills": 0, "perks": {"statPerks": {"defense": 5002, "flex": 5008, "offense": 5007}, "styles": [{"description": "primaryStyle", "selections": [{"perk": 8214, "var1": 425, "var2": 91, "var3": 0}, {"perk": 8226, "var1": 250, "var2": 53, "var3": 0}, {"perk": 8210, "var1": 7, "var2": 0, "var3": 0}, {"perk": 8236, "var1": 24, "var2": 0, "var3": 0}], "style": 8200}, {"description": "subStyle", "selections": [{"perk": 8009, "var1": 2862, "var2": 0, "var3": 0}, {"perk": 8014, "var1": 96, "var2": 0, "var3": 0}], "style": 8000}]}, "physicalDamageDealt": 7623, "physicalDamageDealtToChampions": 819, "physicalDamageTaken": 2657, "profileIcon": 5271, "puuid": "uwBIYGc0A4XQuA2ILGlnlX0sRFg-zwQRaBIUumq2trvOV0YpS73ldfGlaGfwSLU61ojJ4y2ZDE7eUw", "quadraKills": 0, "riotIdName": "", "riotIdTagline": "", "role": "CARRY", "sightWardsBoughtInGame": 0, "spell1Casts": 65, "spell2Casts": 32, "spell3Casts": 43, "spell4Casts": 5, "summoner1Casts": 3, "summoner1Id": 7, "summoner2Casts": 3, "summoner2Id": 4, "summonerId": "t-SU_HuHSPr8NoTamQcwEZXRbtv-6Q1To-HJzv5c-9Z52FI", "summonerLevel": 845, "summonerName": "Swkeeee", "teamEarlySurrendered": false, "teamId": 200, "teamPosition": "BOTTOM", "timeCCingOthers": 7, "timePlayed": 1286, "totalDamageDealt": 62441, "totalDamageDealtToChampions": 5905, "totalDamageShieldedOnTeammates": 1181, "totalDamageTaken": 5208, "totalHeal": 4408, "totalHealsOnTeammates": 3127, "totalMinionsKilled": 135, "totalTimeCCDealt": 93, "totalTimeSpentDead": 14, "totalUnitsHealed": 5, "tripleKills": 0, "trueDamageDealt": 3175, "trueDamageDealtToChampions": 0, "trueDamageTaken": 1328, "turretKills": 0, "turretTakedowns": 4, "turretsLost": 0, "unrealKills": 0, "visionScore": 23, "visionWardsBoughtInGame": 2, "wardsKilled": 2, "wardsPlaced": 8, "win": true}, {"assists": 19, "baronKills": 0, "bountyLevel": 1, "challenges": {"12AssistStreakCount": 0, "abilityUses": 189, "acesBefore15Minutes": 0, "alliedJungleMonsterKills": 0, "baronTakedowns": 0, "blastConeOppositeOpponentCount": 0, "bountyGold": 0, "buffsStolen": 0, "completeSupportQuestInTime": 1, "controlWardTimeCoverageInRiverOrEnemyHalf": 0.01662104786233499, "controlWardsPlaced": 1, "damagePerMinute": 413.6003930896423, "damageTakenOnTeamPercentage": 0.17989610150589455, "dancedWithRiftHerald": 0, "deathsByEnemyChamps": 4, "dodgeSkillShotsSmallWindow": 5, "doubleAces": 0, "dragonTakedowns": 0, "effectiveHealAndShielding": 2370.87841796875, "elderDragonKillsWithOpposingSoul": 0, "elderDragonMultikills": 0, "enemyChampionImmobilizations": 6, "enemyJungleMonsterKills": 0, "epicMonsterKillsNearEnemyJungler": 0, "epicMonsterKillsWithin30SecondsOfSpawn": 0, "epicMonsterSteals": 0, "epicMonsterStolenWithoutSmite": 0, "fasterSupportQuestCompletion": 1, "firstTurretKilledTime": 809.9673709, "flawlessAces": 0, "fullTeamTakedown": 1, "gameLength": 1286.2753827, "getTakedownsInAllLanesEarlyJungleAsLaner": 0, "goldPerMinute": 321.880788167847, "hadAfkTeammate": 0, "hadOpenNexus": 0, "immobilizeAndKillWithAlly": 4, "initialBuffCount": 0, "initialCrabCount": 0, "jungleCsBefore10Minutes": 0, "junglerTakedownsNearDamagedEpicMonster": 0, "kTurretsDestroyedBeforePlatesFall": 0, "kda": 5, "killAfterHiddenWithAlly": 0, "killParticipation": 1.6666666666666667, "killedChampTookFullTeamDamageSurvived": 0, "killsNearEnemyTurret": 0, "killsOnOtherLanesEarlyJungleAsLaner": 0, "killsOnRecentlyHealedByAramPack": 0, "killsUnderOwnTurret": 0, "killsWithHelpFromEpicMonster": 0, "knockEnemyIntoTeamAndKill": 0, "landSkillShotsEarlyGame": 5, "laneMinionsFirst10Minutes": 2, "legendaryCount": 0, "lostAnInhibitor": 0, "maxKillDeficit": 0, "moreEnemyJungleThanOpponent": -115.05000004172325, "multiKillOneSpell": 0, "multiTurretRiftHeraldCount": 1, "multikills": 0, "multikillsAfterAggressiveFlash": 0, "mythicItemUsed": 2065, "outerTurretExecutesBefore10Minutes": 0, "outnumberedKills": 0, "outnumberedNexusKill": 0, "perfectDragonSoulsTaken": 0, "perfectGame": 0, "pickKillWithAlly": 17, "poroExplosions": 0, "quickCleanse": 0, "quickFirstTurret": 1, "quickSoloKills": 0, "riftHeraldTakedowns": 0, "saveAllyFromDeath": 0, "scuttleCrabKills": 0, "skillshotsDodged": 18, "skillshotsHit": 23, "snowballsHit": 0, "soloBaronKills": 0, "soloKills": 0, "soloTurretsLategame": 1, "stealthWardsPlaced": 18, "survivedSingleDigitHpCount": 0, "survivedThreeImmobilizesInFight": 4, "takedownOnFirstTurret": 0, "takedowns": 20, "takedownsAfterGainingLevelAdvantage": 0, "takedownsBeforeJungleMinionSpawn": 0, "takedownsFirstXMinutes": 6, "takedownsInAlcove": 0, "takedownsInEnemyFountain": 0, "teamBaronKills": 0, "teamDamagePercentage": 0.15110786083128674, "teamElderDragonKills": 0, "teamRiftHeraldKills": 1, "threeWardsOneSweeperCount": 0, "tookLargeDamageSurvived": 0, "turretPlatesTaken": 1, "turretTakedowns": 6, "turretsTakenWithRiftHerald": 10, "twentyMinionsIn3SecondsCount": 0, "unseenRecalls": 0, "visionScorePerMinute": 1.7746066343642148, "wardTakedowns": 3, "wardTakedownsBefore20M": 3, "wardsGuarded": 0}, "champExperience": 8141, "champLevel": 11, "championId": 43, "championName": "Karma", "championTransform": 0, "consumablesPurchased": 4, "damageDealtToBuildings": 1967, "damageDealtToObjectives": 1967, "damageDealtToTurrets": 1967, "damageSelfMitigated": 4192, "deaths": 4, "detectorWardsPlaced": 1, "doubleKills": 0, "dragonKills": 0, "eligibleForProgression": true, "firstBloodAssist": false, "firstBloodKill": false, "firstTowerAssist": false, "firstTowerKill": false, "gameEndedInEarlySurrender": false, "gameEndedInSurrender": false, "goldEarned": 6900, "goldSpent": 5825, "individualPosition": "UTILITY", "inhibitorKills": 0, "inhibitorTakedowns": 2, "inhibitorsLost": 0, "item0": 3916, "item1": 2065, "item2": 3853, "item3": 3158, "item4": 4642, "item5": 0, "item6": 3364, "itemsPurchased": 15, "killingSprees": 0, "kills": 1, "lane": "BOTTOM", "largestCriticalStrike": 0, "largestKillingSpree": 0, "largestMultiKill": 1, "longestTimeSpentLiving": 295, "magicDamageDealt": 20238, "magicDamageDealtToChampions": 8032, "magicDamageTaken": 4844, "neutralMinionsKilled": 0, "nexusKills": 0, "nexusLost": 0, "nexusTakedowns": 1, "objectivesStolen": 0, "objectivesStolenAssists": 0, "participantId": 10, "pentaKills": 0, "perks": {"statPerks": {"defense": 5002, "flex": 5008, "offense": 5008}, "styles": [{"description": "primaryStyle", "selections": [{"perk": 8229, "var1": 876, "var2": 0, "var3": 0}, {"perk": 8275, "var1": 8, "var2": 0, "var3": 0}, {"perk": 8233, "var1": 13, "var2": 0, "var3": 0}, {"perk": 8237, "var1": 348, "var2": 0, "var3": 0}], "style": 8200}, {"description": "subStyle", "selections": [{"perk": 8345, "var1": 3, "var2": 0, "var3": 0}, {"perk": 8352, "var1": 48, "var2": 160, "var3": 18}], "style": 8300}]}, "physicalDamageDealt": 2793, "physicalDamageDealtToChampions": 834, "physicalDamageTaken": 2516, "profileIcon": 744, "puuid": "gRdqveymmyp1r-3uSL9i6T8vgHQ0upQBuElh61qgUjqz_6HnKNeBRQ7pc7Do70DQJXDuJkJemdVrHA", "quadraKills": 0, "riotIdName": "", "riotIdTagline": "", "role": "SUPPORT", "sightWardsBoughtInGame": 0, "spell1Casts": 62, "spell2Casts": 19, "spell3Casts": 81, "spell4Casts": 27, "summoner1Casts": 3, "summoner1Id": 4, "summoner2Casts": 5, "summoner2Id": 3, "summonerId": "EpWKTaxoiIJm-ZaJa3zpaM8tiO5twb0YiTH3svjKJ_IeXTw", "summonerLevel": 442, "summonerName": "sigmamale143554", "teamEarlySurrendered": false, "teamId": 200, "teamPosition": "UTILITY", "timeCCingOthers": 20, "timePlayed": 1286, "totalDamageDealt": 23031, "totalDamageDealtToChampions": 8866, "totalDamageShieldedOnTeammates": 2370, "totalDamageTaken": 8627, "totalHeal": 716, "totalHealsOnTeammates": 0, "totalMinionsKilled": 10, "totalTimeCCDealt": 146, "totalTimeSpentDead": 58, "totalUnitsHealed": 1, "tripleKills": 0, "trueDamageDealt": 0, "trueDamageDealtToChampions": 0, "trueDamageTaken": 1265, "turretKills": 1, "turretTakedowns": 6, "turretsLost": 0, "unrealKills": 0, "visionScore": 38, "visionWardsBoughtInGame": 1, "wardsKilled": 3, "wardsPlaced": 19, "win": true}], "platformId": "NA1", "queueId": 420, "teams": [{"bans": [{"championId": 157, "pickTurn": 1}, {"championId": -1, "pickTurn": 2}, {"championId": 107, "pickTurn": 3}, {"championId": 114, "pickTurn": 4}, {"championId": 360, "pickTurn": 5}], "objectives": {"baron": {"first": false, "kills": 0}, "champion": {"first": false, "kills": 12}, "dragon": {"first": true, "kills": 1}, "inhibitor": {"first": false, "kills": 0}, "riftHerald": {"first": false, "kills": 0}, "tower": {"first": false, "kills": 0}}, "teamId": 100, "win": false}, {"bans": [{"championId": 555, "pickTurn": 6}, {"championId": 203, "pickTurn": 7}, {"championId": 37, "pickTurn": 8}, {"championId": 30, "pickTurn": 9}, {"championId": 157, "pickTurn": 10}], "objectives": {"baron": {"first": false, "kills": 0}, "champion": {"first": true, "kills": 35}, "dragon": {"first": false, "kills": 1}, "inhibitor": {"first": true, "kills": 2}, "riftHerald": {"first": true, "kills": 1}, "tower": {"first": true, "kills": 10}}, "teamId": 200, "win": true}], "tournamentCode": ""}}